AUTHORS.rst
CONTRIBUTING.rst
HISTORY.rst
LICENSE
MANIFEST.in
README.rst
setup.cfg
setup.py
docs/Makefile
docs/authors.rst
docs/conf.py
docs/contributing.rst
docs/history.rst
docs/index.rst
docs/installation.rst
docs/make.bat
docs/setting_up.rst
docs/usage.rst
tests/__init__.py
tests/fixtures.py
tests/test_files.py
tests/test_model.py
tests/test_modelrun.py
tucluster/__init__.py
tucluster/app.py
tucluster/conf.py
tucluster.egg-info/PKG-INFO
tucluster.egg-info/SOURCES.txt
tucluster.egg-info/dependency_links.txt
tucluster.egg-info/not-zip-safe
tucluster.egg-info/requires.txt
tucluster.egg-info/top_level.txt