Metadata-Version: 1.1
Name: tucluster
Version: 0.1.0
Summary: HTTP API for managing and running Tuflow models in the cloud
Home-page: https://github.com/JamesRamm/tucluster
Author: James Ramm
Author-email: jamessramm@gmail.com
License: GNU General Public License v3
Keywords: tucluster
Platform: UNKNOWN
Classifier: Development Status :: 2 - Pre-Alpha
Classifier: Intended Audience :: Developers
Classifier: License :: OSI Approved :: GNU General Public License v3 (GPLv3)
Classifier: Natural Language :: English
Classifier: Programming Language :: Python :: 2
Classifier: Programming Language :: Python :: 2.6
Classifier: Programming Language :: Python :: 2.7
Classifier: Programming Language :: Python :: 3
Classifier: Programming Language :: Python :: 3.3
Classifier: Programming Language :: Python :: 3.4
Classifier: Programming Language :: Python :: 3.5
